openthought/__init__.py
openthought/main.py
openthought-0.1.0.dist-info/LICENSE
openthought-0.1.0.dist-info/METADATA
openthought-0.1.0.dist-info/WHEEL
openthought-0.1.0.dist-info/top_level.txt
openthought-0.1.0.dist-info/RECORD
