Metadata-Version: 2.1
Name: openthought
Version: 0.1.0
Summary: openthought package
Home-page: https://github.com/PrimeIntellect-ai/openthought
Author: Jack Min Ong
Author-email: jackmin@primeintellect.ai
Classifier: Programming Language :: Python :: 3
Classifier: License :: OSI Approved :: MIT License
Classifier: Operating System :: OS Independent
Requires-Python: >=3.8
License-File: LICENSE
